fake_http_header/__init__.py
fake_http_header/constants.py
fake_http_header/data_import.py
fake_http_header/fake_http_header.py
fake_http_header/util.py
fake_http_header/data/__init__.py
fake_http_header/data/browser-to-accept-values.json
fake_http_header/data/browser-to-user-agent.json
fake_http_header/data/encoding-values.json
fake_http_header/data/top-level-domain-to-languages.json
fake_http_header/data/top-level-domain-to-search-engines.json
misc/__init__.py
misc/version.py
fake_http_header-0.3.4.dist-info/LICENSE.txt
fake_http_header-0.3.4.dist-info/METADATA
fake_http_header-0.3.4.dist-info/WHEEL
fake_http_header-0.3.4.dist-info/top_level.txt
fake_http_header-0.3.4.dist-info/RECORD
