Metadata-Version: 2.1
Name: fake-http-header
Version: 0.3.4
Summary: Generates random request fields for a http request header
Home-page: https://github.com/MichaelTatarski/fake-http-header
Author: Michael Tatarski
Author-email: michaeltatarski@yahoo.de
License: MIT
Requires-Python: >=3.6
License-File: LICENSE.txt
